main/__init__.py
main/data_fetcher.py
main/setup.py
medco_pi_data_fetcher-0.1.2.dist-info/LICENSE
medco_pi_data_fetcher-0.1.2.dist-info/METADATA
medco_pi_data_fetcher-0.1.2.dist-info/WHEEL
medco_pi_data_fetcher-0.1.2.dist-info/top_level.txt
medco_pi_data_fetcher-0.1.2.dist-info/RECORD
