Metadata-Version: 2.1
Name: medco-pi-data-fetcher
Version: 0.1.2
Summary: A package to fetch data from PI System using PI Web API
Home-page: https://github.com/WigunaKurniawan/medco-pi-data-fetcher
Author: Wiguna Kurniawan
Author-email: youremail@example.com
Classifier: Programming Language :: Python :: 3
Classifier: License :: OSI Approved :: MIT License
Classifier: Operating System :: OS Independent
Requires-Python: >=3.6
License-File: LICENSE
Requires-Dist: requests
Requires-Dist: pandas
